libmsf/__init__.py
libmsf/parser.py
libmsf/rest.py
libmsf-0.2.4.dist-info/METADATA
libmsf-0.2.4.dist-info/WHEEL
libmsf-0.2.4.dist-info/entry_points.txt
libmsf-0.2.4.dist-info/top_level.txt
libmsf-0.2.4.dist-info/RECORD
