Metadata-Version: 2.1
Name: libmsf
Version: 0.2.4
Summary: Python Metasploit Library
Home-page: https://python-libmsf.github.io/
Author: Vladimir Ivanov
Author-email: ivanov.vladimir.mail@gmail.com
License: UNKNOWN
Platform: UNKNOWN
Classifier: Development Status :: 4 - Beta
Classifier: Environment :: Console
Classifier: Intended Audience :: Education
Classifier: License :: OSI Approved :: MIT License
Classifier: Natural Language :: English
Classifier: Operating System :: MacOS
Classifier: Operating System :: Microsoft :: Windows
Classifier: Operating System :: POSIX :: Linux
Classifier: Programming Language :: Python :: 3 :: Only
Classifier: Programming Language :: Python :: 3.6
Classifier: Programming Language :: Python :: 3.7
Classifier: Programming Language :: Python :: 3.8
Classifier: Programming Language :: Python :: 3.9
Classifier: Programming Language :: Python :: 3.10
Classifier: Topic :: Education
Classifier: Topic :: Security
Requires-Python: >=3.6
Requires-Dist: requests
Requires-Dist: urllib3
Requires-Dist: dataclasses
Requires-Dist: marshmallow
Requires-Dist: configparser
